HeatTransfer/Calculos.py
HeatTransfer/__init__.py
HeatTransfer/resistencias/__init__.py
HeatTransfer/resistencias/cilindrico2tubos.py
HeatTransfer/resistencias/areas/__init__.py
HeatTransfer/resistencias/areas/cilindro.py
heattransfer-0.1.0.dist-info/METADATA
heattransfer-0.1.0.dist-info/WHEEL
heattransfer-0.1.0.dist-info/top_level.txt
heattransfer-0.1.0.dist-info/RECORD
