Metadata-Version: 2.4
Name: heattransfer
Version: 0.1.0
Summary: Um pacote para cálculo de transferência de calor entre dois tubos concêntricos.
Home-page: https://github.com/ThiagoLabM
Author: Thiago
Author-email: thiagolablonsk@gmail.com
Classifier: Programming Language :: Python :: 3
Classifier: License :: OSI Approved :: MIT License
Classifier: Operating System :: OS Independent
Requires-Python: >=3.7
Dynamic: author
Dynamic: author-email
Dynamic: classifier
Dynamic: description
Dynamic: description-content-type
Dynamic: home-page
Dynamic: requires-python
Dynamic: summary
